bastionai/__init__.py
bastionai/client.py
bastionai/errors.py
bastionai/learner.py
bastionai/optimizer_config.py
bastionai/utils.py
bastionai/version.py
bastionai/pb/__init__.py
bastionai/pb/remote_torch_pb2.py
bastionai/pb/remote_torch_pb2_grpc.py
bastionai/psg/__init__.py
bastionai/psg/convert.py
bastionai/psg/nn.py
bastionai-0.2.1.dist-info/METADATA
bastionai-0.2.1.dist-info/WHEEL
bastionai-0.2.1.dist-info/top_level.txt
bastionai-0.2.1.dist-info/RECORD
