Metadata-Version: 2.1
Name: bastionai
Version: 0.2.1
Summary: Client SDK for BastionAI Confidential AI Training.
Author: Kwabena Amponsem, Lucas Bourtoule
Author-email: kwabena.amponsem@mithrilsecurity.io, luacs.bourtoule@nithrilsecurity.io
Keywords: confidential computing training client enclave amd-sev machine learning
Classifier: Programming Language :: Python :: 3
Requires-Dist: grpcio (==1.47.0)
Requires-Dist: grpcio-tools (==1.47.0)
Requires-Dist: protobuf (==3.20.1)
Requires-Dist: six (==1.16.0)
Requires-Dist: torch (==1.12.0)
Requires-Dist: numpy (==1.23.1)
Requires-Dist: typing-extensions (==4.3.0)
Requires-Dist: tqdm (==4.64.0)
